console/__init__.py
console/_version.py
console/py.typed
nexus_console-0.0.1.dist-info/licenses/LICENSE
nexus_console-0.0.1.dist-info/METADATA
nexus_console-0.0.1.dist-info/WHEEL
nexus_console-0.0.1.dist-info/entry_points.txt
nexus_console-0.0.1.dist-info/top_level.txt
nexus_console-0.0.1.dist-info/RECORD
