Metadata-Version: 2.4
Name: nexus-console
Version: 0.0.1
Summary: MRI Nexus console application to run pulseq sequences on Spectrum-Instrumentation measurement cards.
Author: Berk Silemek, Thomas O'Reilly
Author-email: David Schote <david.schote@ptb.de>
License: GNU GENERAL PUBLIC LICENSE
Keywords: MRI, console, spectrum-instrumentation, acquisition, pulseq
Classifier: Programming Language :: Python
Classifier: Programming Language :: Python :: 3 :: Only
Requires-Python: <3.13,>=3.10
License-File: LICENSE
Requires-Dist: pypulseq
Requires-Dist: numpy
Requires-Dist: plotly
Requires-Dist: PyYAML
Requires-Dist: matplotlib
Requires-Dist: pandas
Requires-Dist: ismrmrd
Provides-Extra: test
Requires-Dist: pytest; extra == "test"
Requires-Dist: pytest-cov; extra == "test"
Requires-Dist: pytest-xdist; extra == "test"
Requires-Dist: coverage; extra == "test"
Requires-Dist: codecov; extra == "test"
Provides-Extra: lint
Requires-Dist: mypy; extra == "lint"
Requires-Dist: ruff; extra == "lint"
Requires-Dist: types-PyYAML; extra == "lint"
Provides-Extra: docs
Requires-Dist: sphinx; extra == "docs"
Requires-Dist: pydata-sphinx-theme; extra == "docs"
Requires-Dist: sphinx-pyproject; extra == "docs"
Requires-Dist: sphinx-design; extra == "docs"
Provides-Extra: dev
Requires-Dist: line_profiler[ipython]; extra == "dev"
Requires-Dist: nbformat>=4.2.0; extra == "dev"
Requires-Dist: ipykernel; extra == "dev"
Requires-Dist: ipython; extra == "dev"
Requires-Dist: ipywidgets; extra == "dev"
Dynamic: license-file
